{
  "version": "NIV",
  "text": [
    {
      "title": "Judgment on the Whole Earth in the Day of the Lord",
      "text": [
        {
          "text": "The word of the Lord that came to Zephaniah son of Cushi, the son of Gedaliah, the son of Amariah, the son of Hezekiah, during the reign of Josiah son of Amon king of Judah:",
          "ID": "1"
        },
        {
          "text": "“I will sweep away everything\nfrom the face of the earth,”",
          "ID": "2"
        },
        {
          "text": "“I will sweep away both man and beast;\nI will sweep away the birds in the sky\nand the fish in the sea—\nand the idols that cause the wicked to stumble.”\n“When I destroy all mankind\non the face of the earth,”",
          "ID": "3",
          "comments": [
            "The meaning of the Hebrew for this line is uncertain."
          ]
        },
        {
          "text": "“I will stretch out my hand against Judah\nand against all who live in Jerusalem.\nI will destroy every remnant of Baal worship in this place,\nthe very names of the idolatrous priests—",
          "ID": "4"
        },
        {
          "text": "those who bow down on the roofs\nto worship the starry host,\nthose who bow down and swear by the Lord\nand who also swear by Molek,",
          "ID": "5",
          "comments": [
            "Hebrew Malkam"
          ]
        },
        {
          "text": "those who turn back from following the Lord\nand neither seek the Lord nor inquire of him.”",
          "ID": "6"
        },
        {
          "text": "Be silent before the Sovereign Lord,\nfor the day of the Lord is near.\nThe Lord has prepared a sacrifice;\nhe has consecrated those he has invited.",
          "ID": "7"
        },
        {
          "text": "“On the day of the Lord’s sacrifice\nI will punish the officials\nand the king’s sons\nand all those clad\nin foreign clothes.",
          "ID": "8"
        },
        {
          "text": "On that day I will punish\nall who avoid stepping on the threshold,\nwho fill the temple of their gods\nwith violence and deceit.",
          "ID": "9",
          "comments": [
            "See 1 Samuel 5:5."
          ]
        },
        {
          "text": "“On that day,”\ndeclares the Lord,\n“a cry will go up from the Fish Gate,\nwailing from the New Quarter,\nand a loud crash from the hills.",
          "ID": "10"
        },
        {
          "text": "Wail, you who live in the market district;\nall your merchants will be wiped out,\nall who trade with silver will be destroyed.",
          "ID": "11",
          "comments": [
            "Or the Mortar",
            "Or in"
          ]
        },
        {
          "text": "At that time I will search Jerusalem with lamps\nand punish those who are complacent,\nwho are like wine left on its dregs,\nwho think, ‘The Lord will do nothing,\neither good or bad.’",
          "ID": "12"
        },
        {
          "text": "Their wealth will be plundered,\ntheir houses demolished.\nThough they build houses,\nthey will not live in them;\nthough they plant vineyards,\nthey will not drink the wine.”",
          "ID": "13"
        },
        {
          "text": "The great day of the Lord is near—\nnear and coming quickly.\nThe cry on the day of the Lord is bitter;\nthe Mighty Warrior shouts his battle cry.",
          "ID": "14"
        },
        {
          "text": "That day will be a day of wrath—\na day of distress and anguish,\na day of darkness and gloom,",
          "ID": "15"
        },
        {
          "text": "    a day of trumpet and battle cry\nagainst the fortified cities\nand against the corner towers.",
          "ID": "16"
        },
        {
          "text": "“I will bring such distress on all people\nthat they will grope about like those who are blind,\nbecause they have sinned against the Lord.\nTheir blood will be poured out like dust\nand their entrails like dung.",
          "ID": "17"
        },
        {
          "text": "Neither their silver nor their gold\nwill be able to save them\non the day of the Lord’s wrath.”\nIn the fire of his jealousy\nthe whole earth will be consumed,\nfor he will make a sudden end\nof all who live on the earth.",
          "ID": "18"
        }
      ],
      "ID": "OT:ZEP.1",
      "name": "Zephaniah 1"
    },
    {
      "title": "Assyria",
      "text": [
        {
          "text": "Gather together, gather yourselves together,\nyou shameful nation,",
          "ID": "1"
        },
        {
          "text": "before the decree takes effect\nand that day passes like windblown chaff,\nbefore the Lord’s fierce anger\ncomes upon you,\nbefore the day of the Lord’s wrath\ncomes upon you.",
          "ID": "2"
        },
        {
          "text": "Seek the Lord, all you humble of the land,\nyou who do what he commands.\nSeek righteousness, seek humility;\nperhaps you will be sheltered\non the day of the Lord’s anger.",
          "ID": "3"
        },
        {
          "text": "Gaza will be abandoned\nand Ashkelon left in ruins.\nAt midday Ashdod will be emptied\nand Ekron uprooted.",
          "ID": "4"
        },
        {
          "text": "Woe to you who live by the sea,\nyou Kerethite people;\nthe word of the Lord is against you,\nCanaan, land of the Philistines.\nHe says, “I will destroy you,\nand none will be left.”",
          "ID": "5"
        },
        {
          "text": "The land by the sea will become pastures\nhaving wells for shepherds\nand pens for flocks.",
          "ID": "6"
        },
        {
          "text": "That land will belong\nto the remnant of the people of Judah;\nthere they will find pasture.\nIn the evening they will lie down\nin the houses of Ashkelon.\nThe Lord their God will care for them;\nhe will restore their fortunes.",
          "ID": "7",
          "comments": [
            "Or will bring back their captives"
          ]
        },
        {
          "text": "“I have heard the insults of Moab\nand the taunts of the Ammonites,\nwho insulted my people\nand made threats against their land.",
          "ID": "8"
        },
        {
          "text": "Therefore, as surely as I live,”\ndeclares the Lord Almighty,\nthe God of Israel,\n“surely Moab will become like Sodom,\nthe Ammonites like Gomorrah—\na place of weeds and salt pits,\na wasteland forever.\nThe remnant of my people will plunder them;\nthe survivors of my nation will inherit their land.”",
          "ID": "9"
        },
        {
          "text": "This is what they will get in return for their pride,\nfor insulting and mocking\nthe people of the Lord Almighty.",
          "ID": "10"
        },
        {
          "text": "The Lord will be awesome to them\nwhen he destroys all the gods of the earth.\nDistant nations will bow down to him,\nall of them in their own lands.",
          "ID": "11"
        },
        {
          "text": "“You Cushites, too,\nwill be slain by my sword.”",
          "ID": "12",
          "comments": [
            "That is, people from the upper Nile region"
          ]
        },
        {
          "text": "He will stretch out his hand against the north\nand destroy Assyria,\nleaving Nineveh utterly desolate\nand dry as the desert.",
          "ID": "13"
        },
        {
          "text": "Flocks and herds will lie down there,\ncreatures of every kind.\nThe desert owl and the screech owl\nwill roost on her columns.\nTheir hooting will echo through the windows,\nrubble will fill the doorways,\nthe beams of cedar will be exposed.",
          "ID": "14"
        },
        {
          "text": "This is the city of revelry\nthat lived in safety.\nShe said to herself,\n“I am the one! And there is none besides me.”\nWhat a ruin she has become,\na lair for wild beasts!\nAll who pass by her scoff\nand shake their fists.",
          "ID": "15"
        }
      ],
      "ID": "OT:ZEP.2",
      "name": "Zephaniah 2"
    },
    {
      "title": "Restoration of Israel’s Remnant",
      "text": [
        {
          "text": "Woe to the city of oppressors,\nrebellious and defiled!",
          "ID": "1"
        },
        {
          "text": "She obeys no one,\nshe accepts no correction.\nShe does not trust in the Lord,\nshe does not draw near to her God.",
          "ID": "2"
        },
        {
          "text": "Her officials within her\nare roaring lions;\nher rulers are evening wolves,\nwho leave nothing for the morning.",
          "ID": "3"
        },
        {
          "text": "Her prophets are unprincipled;\nthey are treacherous people.\nHer priests profane the sanctuary\nand do violence to the law.",
          "ID": "4"
        },
        {
          "text": "The Lord within her is righteous;\nhe does no wrong.\nMorning by morning he dispenses his justice,\nand every new day he does not fail,\nyet the unrighteous know no shame.",
          "ID": "5"
        },
        {
          "text": "“I have destroyed nations;\ntheir strongholds are demolished.\nI have left their streets deserted,\nwith no one passing through.\nTheir cities are laid waste;\nthey are deserted and empty.",
          "ID": "6"
        },
        {
          "text": "Of Jerusalem I thought,\n‘Surely you will fear me\nand accept correction!’\nThen her place of refuge would not be destroyed,\nnor all my punishments come upon her.\nBut they were still eager\nto act corruptly in all they did.",
          "ID": "7",
          "comments": [
            "Or her sanctuary",
            "Or all those I appointed over"
          ]
        },
        {
          "text": "Therefore wait for me,”\ndeclares the Lord,\n“for the day I will stand up to testify.\nI have decided to assemble the nations,\nto gather the kingdoms\nand to pour out my wrath on them—\nall my fierce anger.\nThe whole world will be consumed\nby the fire of my jealous anger.",
          "ID": "8",
          "comments": [
            "Septuagint and Syriac; Hebrew will rise up to plunder"
          ]
        },
        {
          "text": "“Then I will purify the lips of the peoples,\nthat all of them may call on the name of the Lord\nand serve him shoulder to shoulder.",
          "ID": "9"
        },
        {
          "text": "From beyond the rivers of Cush\nmy worshipers, my scattered people,\nwill bring me offerings.",
          "ID": "10",
          "comments": [
            "That is, the upper Nile region"
          ]
        },
        {
          "text": "On that day you, Jerusalem, will not be put to shame\nfor all the wrongs you have done to me,\nbecause I will remove from you\nyour arrogant boasters.\nNever again will you be haughty\non my holy hill.",
          "ID": "11"
        },
        {
          "text": "But I will leave within you\nthe meek and humble.\nThe remnant of Israel\nwill trust in the name of the Lord.",
          "ID": "12"
        },
        {
          "text": "They will do no wrong;\nthey will tell no lies.\nA deceitful tongue\nwill not be found in their mouths.\nThey will eat and lie down\nand no one will make them afraid.”",
          "ID": "13"
        },
        {
          "text": "Sing, Daughter Zion;\nshout aloud, Israel!\nBe glad and rejoice with all your heart,\nDaughter Jerusalem!",
          "ID": "14"
        },
        {
          "text": "The Lord has taken away your punishment,\nhe has turned back your enemy.\nThe Lord, the King of Israel, is with you;\nnever again will you fear any harm.",
          "ID": "15"
        },
        {
          "text": "On that day\nthey will say to Jerusalem,\n“Do not fear, Zion;\ndo not let your hands hang limp.",
          "ID": "16"
        },
        {
          "text": "The Lord your God is with you,\nthe Mighty Warrior who saves.\nHe will take great delight in you;\nin his love he will no longer rebuke you,\nbut will rejoice over you with singing.”",
          "ID": "17"
        },
        {
          "text": "“I will remove from you\nall who mourn over the loss of your appointed festivals,\nwhich is a burden and reproach for you.",
          "ID": "18"
        },
        {
          "text": "At that time I will deal\nwith all who oppressed you.\nI will rescue the lame;\nI will gather the exiles.\nI will give them praise and honor\nin every land where they have suffered shame.",
          "ID": "19"
        },
        {
          "text": "At that time I will gather you;\nat that time I will bring you home.\nI will give you honor and praise\namong all the peoples of the earth\nwhen I restore your fortunes\nbefore your very eyes,”",
          "ID": "20",
          "comments": [
            "Or I bring back your captives"
          ]
        }
      ],
      "ID": "OT:ZEP.3",
      "name": "Zephaniah 3"
    }
  ],
  "ID": "OT:ZEP(NIV)",
  "name": "Zephaniah"
}